Divider_implementation/iteration.v
// ==========================================================
// 1. NR Stage (2-Cycle Balanced Pipeline) - Verilog-2001
// ==========================================================
module nr_iteration_stage #(parameter WIDTH = 32, FRAC = 16)(
    input clk, rst,
    input signed [WIDTH-1:0] a_in, b_in, x_in,
    output signed [WIDTH-1:0] a_out, b_out, x_out
);
    localparam signed [WIDTH-1:0] CONST_2 = 2 << FRAC;

    reg signed [WIDTH-1:0] a_r1, b_r1, x_r1;
    reg signed [WIDTH-1:0] a_r2, b_r2, x_r2;
    reg signed [63:0] mul1;

    // Stage 1
    always @(posedge clk) begin
        if (rst) begin
            mul1 <= 0; a_r1 <= 0; b_r1 <= 0; x_r1 <= 0;
        end else begin
            mul1 <= b_in * x_in;
            a_r1 <= a_in; b_r1 <= b_in; x_r1 <= x_in;
        end
    end

    // Stage 2
    always @(posedge clk) begin
        if (rst) begin
            x_r2 <= 0; a_r2 <= 0; b_r2 <= 0;
        end else begin
            x_r2 <= (x_r1 * (CONST_2 - (mul1 >>> FRAC))) >>> FRAC;
            a_r2 <= a_r1; b_r2 <= b_r1;
        end
    end

    assign a_out = a_r2;
    assign b_out = b_r2;
    assign x_out = x_r2;
endmodule

Divider_implementation/divider.v
// ==========================================================
// 2. Top-Level Divider - Verilog-2001
// ==========================================================
module nr_divider_top(
    input clk, rst,
    input signed [31:0] dividend, divisor,
    output signed [31:0] quotient
);
    reg signed [31:0] x_seed;
    reg [3:0] d_high;

    wire signed [31:0] a_bus0, a_bus1, a_bus2, a_bus3, a_bus4;
    wire signed [31:0] b_bus0, b_bus1, b_bus2, b_bus3, b_bus4;
    wire signed [31:0] x_bus0, x_bus1, x_bus2, x_bus3, x_bus4;

    assign a_bus0 = dividend;
    assign b_bus0 = divisor;

    // LUT for x0
    always @(*) begin
        d_high = divisor[19:16];
        case(d_high)
            4'h0: x_seed = 32'sh0001_0000; 4'h1: x_seed = 32'sh0000_FFFF;
            4'h2: x_seed = 32'sh0000_8000; 4'h3: x_seed = 32'sh0000_5555;
            4'h4: x_seed = 32'sh0000_4000; 4'h5: x_seed = 32'sh0000_3333;
            4'h6: x_seed = 32'sh0000_2AAA; 4'h7: x_seed = 32'sh0000_2492;
            4'h8: x_seed = 32'sh0000_2000; 4'h9: x_seed = 32'sh0000_1C71;
            4'hA: x_seed = 32'sh0000_1999; 4'hB: x_seed = 32'sh0000_1745;
            4'hC: x_seed = 32'sh0000_1555; 4'hD: x_seed = 32'sh0000_1249;
            4'hE: x_seed = 32'sh0000_1111; 4'hF: x_seed = 32'sh0000_1000;
            default: x_seed = 32'sh0001_0000;
        endcase
    end
    assign x_bus0 = x_seed;

    // NR pipeline
    nr_iteration_stage #(32,16) stage0(clk,rst,a_bus0,b_bus0,x_bus0,a_bus1,b_bus1,x_bus1);
    nr_iteration_stage #(32,16) stage1(clk,rst,a_bus1,b_bus1,x_bus1,a_bus2,b_bus2,x_bus2);
    nr_iteration_stage #(32,16) stage2(clk,rst,a_bus2,b_bus2,x_bus2,a_bus3,b_bus3,x_bus3);
    nr_iteration_stage #(32,16) stage3(clk,rst,a_bus3,b_bus3,x_bus3,a_bus4,b_bus4,x_bus4);

    // Final multiply
    reg signed [63:0] f_mul;
    always @(posedge clk) begin
        if (rst) f_mul <= 0;
        else f_mul <= a_bus4 * x_bus4;
    end
    assign quotient = f_mul >>> 16;
endmodule

Divider_implementation/divider_tb.v
// ==========================================================
// 3. Testbench - Verilog-2001
// ==========================================================
module tb_nr_divider;
    reg clk, rst;
    reg signed [31:0] da, db;
    wire signed [31:0] qq;
    real ra, rb, rq;

    nr_divider_top dut(clk,rst,da,db,qq);

    // Clock generation
    initial begin
        clk = 0; 
        forever #5 clk = ~clk; 
    end

    // Q16 to real conversion
    always @(posedge clk) begin
        ra = $itor(da) / 65536.0;
        rb = $itor(db) / 65536.0;
        rq = $itor(qq) / 65536.0;
    end

    // VCD waveform dumping
    initial begin
        $dumpfile("simulation.vcd");
        $dumpvars(0, tb_nr_divider);
    end

    // Test sequence
    initial begin
        rst = 1; da = 0; db = 1; #20; 
        rst = 0;

        da = 10 << 16; db = 2 << 16; #100;
        $display("10 / 2 = %0.6f", rq);

        da = 8 << 16; db = 4 << 16; #100;
        $display("8 / 4 = %0.6f", rq);

        da = 21 << 16; db = 3 << 16; #100;
        $display("21 / 3 = %0.6f", rq);

        #200 $finish;
    end
endmodule

Divider_implementation/simulation.vcd
$date
	Sat Mar 14 16:59:55 2026
$end
$version
	Icarus Verilog
$end
$timescale
	1s
$end
$scope module tb_nr_divider $end
$var wire 32 ! qq [31:0] $end
$var reg 1 " clk $end
$var reg 32 # da [31:0] $end
$var reg 32 $ db [31:0] $end
$var reg 1 % rst $end
$var real 1 & ra $end
$var real 1 ' rb $end
$var real 1 ( rq $end
$scope module dut $end
$var wire 32 ) a_bus0 [31:0] $end
$var wire 32 * b_bus0 [31:0] $end
$var wire 1 " clk $end
$var wire 32 + dividend [31:0] $end
$var wire 32 , divisor [31:0] $end
$var wire 1 % rst $end
$var wire 32 - x_bus0 [31:0] $end
$var wire 32 . x_bus4 [31:0] $end
$var wire 32 / x_bus3 [31:0] $end
$var wire 32 0 x_bus2 [31:0] $end
$var wire 32 1 x_bus1 [31:0] $end
$var wire 32 2 quotient [31:0] $end
$var wire 32 3 b_bus4 [31:0] $end
$var wire 32 4 b_bus3 [31:0] $end
$var wire 32 5 b_bus2 [31:0] $end
$var wire 32 6 b_bus1 [31:0] $end
$var wire 32 7 a_bus4 [31:0] $end
$var wire 32 8 a_bus3 [31:0] $end
$var wire 32 9 a_bus2 [31:0] $end
$var wire 32 : a_bus1 [31:0] $end
$var reg 4 ; d_high [3:0] $end
$var reg 64 < f_mul [63:0] $end
$var reg 32 = x_seed [31:0] $end
$scope module stage0 $end
$var wire 32 > a_in [31:0] $end
$var wire 32 ? a_out [31:0] $end
$var wire 32 @ b_in [31:0] $end
$var wire 32 A b_out [31:0] $end
$var wire 1 " clk $end
$var wire 1 % rst $end
$var wire 32 B x_in [31:0] $end
$var wire 32 C x_out [31:0] $end
$var parameter 32 D CONST_2 $end
$var parameter 32 E FRAC $end
$var parameter 32 F WIDTH $end
$var reg 32 G a_r1 [31:0] $end
$var reg 32 H a_r2 [31:0] $end
$var reg 32 I b_r1 [31:0] $end
$var reg 32 J b_r2 [31:0] $end
$var reg 64 K mul1 [63:0] $end
$var reg 32 L x_r1 [31:0] $end
$var reg 32 M x_r2 [31:0] $end
$upscope $end
$scope module stage1 $end
$var wire 32 N a_in [31:0] $end
$var wire 32 O a_out [31:0] $end
$var wire 32 P b_in [31:0] $end
$var wire 32 Q b_out [31:0] $end
$var wire 1 " clk $end
$var wire 1 % rst $end
$var wire 32 R x_in [31:0] $end
$var wire 32 S x_out [31:0] $end
$var parameter 32 T CONST_2 $end
$var parameter 32 U FRAC $end
$var parameter 32 V WIDTH $end
$var reg 32 W a_r1 [31:0] $end
$var reg 32 X a_r2 [31:0] $end
$var reg 32 Y b_r1 [31:0] $end
$var reg 32 Z b_r2 [31:0] $end
$var reg 64 [ mul1 [63:0] $end
$var reg 32 \ x_r1 [31:0] $end
$var reg 32 ] x_r2 [31:0] $end
$upscope $end
$scope module stage2 $end
$var wire 32 ^ a_in [31:0] $end
$var wire 32 _ a_out [31:0] $end
$var wire 32 ` b_in [31:0] $end
$var wire 32 a b_out [31:0] $end
$var wire 1 " clk $end
$var wire 1 % rst $end
$var wire 32 b x_in [31:0] $end
$var wire 32 c x_out [31:0] $end
$var parameter 32 d CONST_2 $end
$var parameter 32 e FRAC $end
$var parameter 32 f WIDTH $end
$var reg 32 g a_r1 [31:0] $end
$var reg 32 h a_r2 [31:0] $end
$var reg 32 i b_r1 [31:0] $end
$var reg 32 j b_r2 [31:0] $end
$var reg 64 k mul1 [63:0] $end
$var reg 32 l x_r1 [31:0] $end
$var reg 32 m x_r2 [31:0] $end
$upscope $end
$scope module stage3 $end
$var wire 32 n a_in [31:0] $end
$var wire 32 o a_out [31:0] $end
$var wire 32 p b_in [31:0] $end
$var wire 32 q b_out [31:0] $end
$var wire 1 " clk $end
$var wire 1 % rst $end
$var wire 32 r x_in [31:0] $end
$var wire 32 s x_out [31:0] $end
$var parameter 32 t CONST_2 $end
$var parameter 32 u FRAC $end
$var parameter 32 v WIDTH $end
$var reg 32 w a_r1 [31:0] $end
$var reg 32 x a_r2 [31:0] $end
$var reg 32 y b_r1 [31:0] $end
$var reg 32 z b_r2 [31:0] $end
$var reg 64 { mul1 [63:0] $end
$var reg 32 | x_r1 [31:0] $end
$var reg 32 } x_r2 [31:0] $end
$upscope $end
$upscope $end
$upscope $end
$enddefinitions $end
$comment Show the parameter values. $end
$dumpall
b100000 v
b10000 u
b100000000000000000 t
b100000 f
b10000 e
b100000000000000000 d
b100000 V
b10000 U
b100000000000000000 T
b100000 F
b10000 E
b100000000000000000 D
$end
#0
$dumpvars
bx }
bx |
bx {
bx z
bx y
bx x
bx w
bx s
bx r
bx q
bx p
bx o
bx n
bx m
bx l
bx k
bx j
bx i
bx h
bx g
bx c
bx b
bx a
bx `
bx _
bx ^
bx ]
bx \
bx [
bx Z
bx Y
bx X
bx W
bx S
bx R
bx Q
bx P
bx O
bx N
bx M
bx L
bx K
bx J
bx I
bx H
bx G
bx C
b10000000000000000 B
bx A
b1 @
bx ?
b0 >
b10000000000000000 =
bx <
b0 ;
bx :
bx 9
bx 8
bx 7
bx 6
bx 5
bx 4
bx 3
bx 2
bx 1
bx 0
bx /
bx .
b10000000000000000 -
b1 ,
b0 +
b1 *
b0 )
r0 (
r0 '
r0 &
1%
b1 $
b0 #
0"
bx !
$end
#5
b0 !
b0 2
b0 L
b0 I
b0 G
b0 K
b0 6
b0 A
b0 P
b0 J
b0 :
b0 ?
b0 N
b0 H
b0 1
b0 C
b0 R
b0 M
b0 \
b0 Y
b0 W
b0 [
b0 5
b0 Q
b0 `
b0 Z
b0 9
b0 O
b0 ^
b0 X
b0 0
b0 S
b0 b
b0 ]
b0 l
b0 i
b0 g
b0 k
b0 4
b0 a
b0 p
b0 j
b0 8
b0 _
b0 n
b0 h
b0 /
b0 c
b0 r
b0 m
b0 |
b0 y
b0 w
b0 {
b0 3
b0 q
b0 z
b0 7
b0 o
b0 x
b0 .
b0 s
b0 }
b0 <
r1.52587890625e-05 '
1"
#10
0"
#15
1"
#20
b1000000000000000 -
b1000000000000000 B
b1000000000000000 =
b10 ;
0"
b100000000000000000 *
b100000000000000000 @
b100000000000000000 $
b100000000000000000 ,
b10100000000000000000 )
b10100000000000000000 >
b10100000000000000000 #
b10100000000000000000 +
0%
#25
b1000000000000000 L
b100000000000000000 I
b10100000000000000000 G
b100000000000000000000000000000000 K
r2 '
r10 &
1"
#30
0"
#35
b100000000000000000 6
b100000000000000000 A
b100000000000000000 P
b100000000000000000 J
b10100000000000000000 :
b10100000000000000000 ?
b10100000000000000000 N
b10100000000000000000 H
b1000000000000000 1
b1000000000000000 C
b1000000000000000 R
b1000000000000000 M
1"
#40
0"
#45
b1000000000000000 \
b100000000000000000 Y
b10100000000000000000 W
b100000000000000000000000000000000 [
1"
#50
0"
#55
b100000000000000000 5
b100000000000000000 Q
b100000000000000000 `
b100000000000000000 Z
b10100000000000000000 9
b10100000000000000000 O
b10100000000000000000 ^
b10100000000000000000 X
b1000000000000000 0
b1000000000000000 S
b1000000000000000 b
b1000000000000000 ]
1"
#60
0"
#65
b1000000000000000 l
b100000000000000000 i
b10100000000000000000 g
b100000000000000000000000000000000 k
1"
#70
0"
#75
b100000000000000000 4
b100000000000000000 a
b100000000000000000 p
b100000000000000000 j
b10100000000000000000 8
b10100000000000000000 _
b10100000000000000000 n
b10100000000000000000 h
b1000000000000000 /
b1000000000000000 c
b1000000000000000 r
b1000000000000000 m
1"
#80
0"
#85
b1000000000000000 |
b100000000000000000 y
b10100000000000000000 w
b100000000000000000000000000000000 {
1"
#90
0"
#95
b100000000000000000 3
b100000000000000000 q
b100000000000000000 z
b10100000000000000000 7
b10100000000000000000 o
b10100000000000000000 x
b1000000000000000 .
b1000000000000000 s
b1000000000000000 }
1"
#100
0"
#105
b1010000000000000000 !
b1010000000000000000 2
b10100000000000000000000000000000000 <
1"
#110
0"
#115
r5 (
1"
#120
b100000000000000 -
b100000000000000 B
b100000000000000 =
b100 ;
0"
b1000000000000000000 *
b1000000000000000000 @
b1000000000000000000 $
b1000000000000000000 ,
b10000000000000000000 )
b10000000000000000000 >
b10000000000000000000 #
b10000000000000000000 +
#125
b100000000000000 L
b1000000000000000000 I
b10000000000000000000 G
r4 '
r8 &
1"
#130
0"
#135
b1000000000000000000 6
b1000000000000000000 A
b1000000000000000000 P
b1000000000000000000 J
b10000000000000000000 :
b10000000000000000000 ?
b10000000000000000000 N
b10000000000000000000 H
b100000000000000 1
b100000000000000 C
b100000000000000 R
b100000000000000 M
1"
#140
0"
#145
b100000000000000 \
b1000000000000000000 Y
b10000000000000000000 W
1"
#150
0"
#155
b1000000000000000000 5
b1000000000000000000 Q
b1000000000000000000 `
b1000000000000000000 Z
b10000000000000000000 9
b10000000000000000000 O
b10000000000000000000 ^
b10000000000000000000 X
b100000000000000 0
b100000000000000 S
b100000000000000 b
b100000000000000 ]
1"
#160
0"
#165
b100000000000000 l
b1000000000000000000 i
b10000000000000000000 g
1"
#170
0"
#175
b1000000000000000000 4
b1000000000000000000 a
b1000000000000000000 p
b1000000000000000000 j
b10000000000000000000 8
b10000000000000000000 _
b10000000000000000000 n
b10000000000000000000 h
b100000000000000 /
b100000000000000 c
b100000000000000 r
b100000000000000 m
1"
#180
0"
#185
b100000000000000 |
b1000000000000000000 y
b10000000000000000000 w
1"
#190
0"
#195
b1000000000000000000 3
b1000000000000000000 q
b1000000000000000000 z
b10000000000000000000 7
b10000000000000000000 o
b10000000000000000000 x
b100000000000000 .
b100000000000000 s
b100000000000000 }
1"
#200
0"
#205
b100000000000000000 !
b100000000000000000 2
b1000000000000000000000000000000000 <
1"
#210
0"
#215
r2 (
1"
#220
b101010101010101 -
b101010101010101 B
b101010101010101 =
b11 ;
0"
b110000000000000000 *
b110000000000000000 @
b110000000000000000 $
b110000000000000000 ,
b101010000000000000000 )
b101010000000000000000 >
b101010000000000000000 #
b101010000000000000000 +
#225
b101010101010101 L
b110000000000000000 I
b101010000000000000000 G
b11111111111111110000000000000000 K
r3 '
r21 &
1"
#230
0"
#235
b110000000000000000 6
b110000000000000000 A
b110000000000000000 P
b110000000000000000 J
b101010000000000000000 :
b101010000000000000000 ?
b101010000000000000000 N
b101010000000000000000 H
b101010101010101 1
b101010101010101 C
b101010101010101 R
b101010101010101 M
1"
#240
0"
#245
b101010101010101 \
b110000000000000000 Y
b101010000000000000000 W
b11111111111111110000000000000000 [
1"
#250
0"
#255
b110000000000000000 5
b110000000000000000 Q
b110000000000000000 `
b110000000000000000 Z
b101010000000000000000 9
b101010000000000000000 O
b101010000000000000000 ^
b101010000000000000000 X
b101010101010101 0
b101010101010101 S
b101010101010101 b
b101010101010101 ]
1"
#260
0"
#265
b101010101010101 l
b110000000000000000 i
b101010000000000000000 g
b11111111111111110000000000000000 k
1"
#270
0"
#275
b110000000000000000 4
b110000000000000000 a
b110000000000000000 p
b110000000000000000 j
b101010000000000000000 8
b101010000000000000000 _
b101010000000000000000 n
b101010000000000000000 h
b101010101010101 /
b101010101010101 c
b101010101010101 r
b101010101010101 m
1"
#280
0"
#285
b101010101010101 |
b110000000000000000 y
b101010000000000000000 w
b11111111111111110000000000000000 {
1"
#290
0"
#295
b110000000000000000 3
b110000000000000000 q
b110000000000000000 z
b101010000000000000000 7
b101010000000000000000 o
b101010000000000000000 x
b101010101010101 .
b101010101010101 s
b101010101010101 }
1"
#300
0"
#305
b1101111111111111001 !
b1101111111111111001 2
b11011111111111110010000000000000000 <
1"
#310
0"
#315
r6.999893188476562 (
1"
